LICENCE.txt
MANIFEST.in
README.rst
setup.py
docs/basics.rst
docs/changelog.rst
docs/index.rst
docs/usage.rst
emencia_django_socialaggregator.egg-info/PKG-INFO
emencia_django_socialaggregator.egg-info/SOURCES.txt
emencia_django_socialaggregator.egg-info/dependency_links.txt
emencia_django_socialaggregator.egg-info/not-zip-safe
emencia_django_socialaggregator.egg-info/requires.txt
emencia_django_socialaggregator.egg-info/top_level.txt
socialaggregator/__init__.py
socialaggregator/admin.py
socialaggregator/cms_plugins.py
socialaggregator/cms_toolbar.py
socialaggregator/formatter.py
socialaggregator/models.py
socialaggregator/settings.py
socialaggregator/urls.py
socialaggregator/views.py
socialaggregator/locale/en/LC_MESSAGES/django.po
socialaggregator/locale/fr/LC_MESSAGES/django.po
socialaggregator/management/__init__.py
socialaggregator/management/commands/__init__.py
socialaggregator/management/commands/aggregate.py
socialaggregator/migrations/0001_initial.py
socialaggregator/migrations/0002_auto__add_field_ressource_social_id__add_field_ressource_activate__add.py
socialaggregator/migrations/0003_auto__add_field_ressource_social_type.py
socialaggregator/migrations/0004_auto__chg_field_aggregator_social_plugin__chg_field_ressource_social_t.py
socialaggregator/migrations/0005_auto__add_field_ressource_language.py
socialaggregator/migrations/0006_auto__add_field_ressource_query.py
socialaggregator/migrations/0007_auto__add_field_ressource_update_date.py
socialaggregator/migrations/0008_auto__add_field_ressource_view_size.py
socialaggregator/migrations/0009_auto__add_field_ressource_text_display__chg_field_ressource_view_size.py
socialaggregator/migrations/0010_auto__add_field_ressource_media_url__add_field_ressource_media_url_typ.py
socialaggregator/migrations/0011_auto__add_field_ressource_updated__chg_field_ressource_creation_date__.py
socialaggregator/migrations/0012_auto__add_field_ressource_button_label.py
socialaggregator/migrations/0013_auto__add_field_ressource_button_color.py
socialaggregator/migrations/0014_auto__chg_field_ressource_media_url.py
socialaggregator/migrations/0015_auto__add_field_ressource_background_color__add_field_new_page.py
socialaggregator/migrations/0016_auto__add_feedplugin__chg_field_ressource_image__chg_field_ressource_t.py
