Metadata-Version: 1.1
Name: emencia-django-socialaggregator
Version: 0.3.1
Summary: Django app for aggregate some feeds from social networks.
Home-page: http://emencia.fr/
Author: rage2000
Author-email: lafaye@emencia.com
License: AGPL License
Keywords: django,emencia,social networks,aggregation
Platform: UNKNOWN
Classifier: Framework :: Django
Classifier: Programming Language :: Python :: 2.6
Classifier: Programming Language :: Python :: 2.7
Classifier: Environment :: Web Environment
Classifier: Intended Audience :: Developers
Classifier: Operating System :: OS Independent
Classifier: License :: OSI Approved :: GNU Affero General Public License v3
Classifier: Development Status :: 5 - Production/Stable
Classifier: Topic :: Software Development :: Libraries :: Python Modules
